falra_run/__init__.py
falra_run/falra_run.py
falra_run-0.1.0.dist-info/METADATA
falra_run-0.1.0.dist-info/WHEEL
falra_run-0.1.0.dist-info/top_level.txt
falra_run-0.1.0.dist-info/RECORD
