Metadata-Version: 2.1
Name: falra-run
Version: 0.1.0
Summary: FastAPI dynamic run python package
Home-page: https://github.com/bohachu/falra_run
Author: Bowen Chiu
Author-email: cbh@cameo.tw
License: UNKNOWN
Platform: UNKNOWN
Classifier: Programming Language :: Python :: 3
Classifier: License :: OSI Approved :: MIT License
Classifier: Operating System :: OS Independent
